geospace/__init__.py
geospace/_const.py
geospace/array.py
geospace/boundary.py
geospace/calculator.py
geospace/gee_export.py
geospace/mask.py
geospace/projection.py
geospace/ras_to_shp.py
geospace/raster.py
geospace/shape.py
geospace/shp_to_ras.py
geospace/spatial_calc.py
geospace/stats.py
geospace/utils.py
geospace/zonal.py
geospace-0.5.3.dist-info/WHEEL
geospace-0.5.3.dist-info/METADATA
geospace-0.5.3.dist-info/RECORD
