Metadata-Version: 2.4
Name: geospace
Version: 0.5.3
Summary: Geospatial processing library based on GDAL and Google Earth Engine
Author: Cody James
Author-email: Cody James <xiejx5@gmail.com>
License-Expression: MIT
Requires-Dist: numpy
Requires-Dist: gdal
Requires-Dist: pandas
Requires-Dist: openpyxl
Requires-Dist: tqdm
Requires-Dist: requests ; extra == 'gee'
Requires-Dist: earthengine-api ; extra == 'gee'
Requires-Dist: cartopy ; extra == 'mask'
Requires-Dist: scikit-image ; extra == 'mask'
Requires-Python: >=3.8
Project-URL: homepage, https://github.com/xiejx5/geospace
Provides-Extra: gee
Provides-Extra: mask
